Workbook

Sheet 看板首页
A1: g654321.com 商业化指标看板
A2: 数据更新时间：2026-05-28 18:00（截至5/28下午）；趋势数据为 2026-04-28 ~ 2026-05-27 完整 30 天
A4: 一、累计大盘（来源：系统统计 > 系统统计 卡片）
A6: 会员总数 | B6: 5612182 | C6: 总注册用户数
A7: 付费人数 | B7: 80375 | C7: 总付费用户数（付费渗透率=付费/注册）
A8: 总充值（元） | B8: 7528032 | C8: 总订单 301,697 / 有效 148,659 / 客单价 50.64
A9: 游戏总下载量 | B9: 4252320
A10: 总充值 G 点 | B10: 82377968 | C10: 含赠送 2,584,663；结余 9,316,518
A11: 总消费 G 点 | B11: 75646113
A12: G 点结余 | B12: 9316518 | C12: 健康度：充消比 ≈ 109%
A14: 二、关键 KPI（近 30 天 vs 上一周期 / 数据源：系统统计-报表）
A16: 指标 | B16: 近 7 天 | C16: 近 30 天 | D16: 昨日(5/27) | E16: 说明
A17: 总充值（元） | B17: =SUM('日明细30天'!E5:E11) | C17: =SUM('日明细30天'!E5:E34) | D17: ='日明细30天'!E5
A18: 总订单数 | B18: =SUM('日明细30天'!L5:L11) | C18: =SUM('日明细30天'!L5:L34) | D18: ='日明细30天'!L5
A19: 有效订单数 | B19: =SUM('日明细30天'!M5:M11) | C19: =SUM('日明细30天'!M5:M34) | D19: ='日明细30天'!M5
A20: 退款金额 | B20: =SUM('日明细30天'!F5:F11) | C20: =SUM('日明细30天'!F5:F34) | D20: ='日明细30天'!F5
A21: 日活（平均） | B21: =AVERAGE('日明细30天'!B5:B11) | C21: =AVERAGE('日明细30天'!B5:B34) | D21: ='日明细30天'!B5 | E21: 近7/30天为日均
A22: 注册 | B22: =SUM('日明细30天'!C5:C11) | C22: =SUM('日明细30天'!C5:C34) | D22: ='日明细30天'!C5
A23: 新注册付费人数 | B23: =SUM('日明细30天'!H5:H11) | C23: =SUM('日明细30天'!H5:H34) | D23: ='日明细30天'!H5
A26: 三、阶段建议
A28: 🔴 P0 - 优先处理：
A29: • 修「日活统计」页 bug（所有日期范围无数据）→ 留存看板的根基
A30: • 让技术补「付费分层 5 档」（小R/中R/大R/超R/鲸鱼R）
A31: • 平台维度 LTV/留存（当前只有按游戏，需聚合）
A33: 🟡 P1 - 派生指标：
A34: • 复购率（订单管理已有原始数据，需技术聚合）
A35: • WAU/MAU 严格去重口径
A36: • 沉睡/苏醒付费用户标签
A38: 🟢 已直接可用：
A39: • 系统统计-报表 14 字段全（含退款"投诉扣款"+ 新vs留存付费拆分）
A40: • 套餐统计完整漏斗 + G点档位 + 会员套餐
... A43: • 渠道统计完整分渠道数据

Sheet 口径说明
A1: 指标口径与后台位置映射表
A2: 说明：✅ 直接可见 | ⚙️ 派生可算 | 🔧 待技术 | ⚠️ Bug / 权限
A4: 板块 | B4: 指标 | C4: 后台状态 | D4: 后台位置（已验证） | E4: 取数说明 | F4: 优先级
A5: ✅直接可见 | B5: 系统统计>系统统计>"会员总数"卡片 | C5: 主数字 5 | D5: 612 | E5: 182 | F5: P0
A6: ✅直接可见 | B6: 系统统计>系统统计>"会员总数"卡片副文本 | C6: 付费人数:80,375 | D6: P0
A7: ✅直接可见 | B7: 系统统计>系统统计>"游戏总消费G点"卡片副文本 | C7: G点充值总额:82,377,968 | D7: P0
A8: ✅直接可见 | B8: 系统统计>系统统计>"游戏总消费G点"卡片主数字 | C8: 75 | D8: 646 | E8: 113 | F8: P0
A9: ✅直接可见 | B9: 系统统计>系统统计>"游戏总消费G点"卡片副文本 | C9: G点结余:9,316,518 | D9: P0
A10: ⚙️派生可算 | B10: 系统统计>系统统计 | C10: 付费人数 / 会员总数 | D10: P0
A11: ⚙️派生可算 | B11: 系统统计-报表 | C11: (注册付费人数+留存付费人数) / 日活，按日 | D11: P0
A12: ⚙️派生可算 | B12: 系统统计-报表 | C12: (注册付费金额+留存付费金额) / 日活，按日 | D12: P0
A13: ✅直接可见 | B13: 系统统计>系统统计>"充值"卡片副文本 | C13: 单价字段（已有 50.64/59.64/61.02 等） | D13: P0
A14: ✅直接可见 | B14: 系统统计>系统统计>"充值"卡片副文本 | C14: 同 ARPPU 字段（实质就是订单平均金额） | D14: P0
A15: ⚠️间接 | B15: 系统统计-报表 | C15: 今日还没结算时无值；可临时用今日充值卡的订单人数近似 | D15: P0
A16: ✅直接可见 | B16: 系统统计>系统统计>"今日注册"卡片 | C16: 16218（更新时间 05-28 18:00） | D16: P0
A17: ⚠️间接 | B17: 系统统计>系统统计>"今日充值"卡片 | C17: 卡里"总订单数1391"是订单数不是UV；UV需技术加 | D17: P0
A18: ✅直接可见 | B18: 系统统计>系统统计>"今日游戏消费G点"卡片副文本 | C18: G点充值总额:466,837 | D18: P0
A19: ✅直接可见 | B19: 系统统计>系统统计>"今日游戏消费G点"卡片主数字 | C19: 620 | D19: 681 | E19: P0
A20: ⚙️派生可算 | B20: 系统统计-报表 | C20: 总充值 - 网游消费（需技术明确口径） | D20: P0
A21: ✅直接可见 | B21: 网络游戏运营统计>当日加总 | C21: 可按日期搜+导出 | D21: P0
A22: ✅直接可见 | B22: 系统统计>系统统计>"今日游戏下载数量"卡片 | C22: 14630 | D22: P0
A23: ✅直接可见 | B23: 网络游戏运营统计>当日"新增账号"加总 | C23: 可按日期搜+导出 | D23: P0
A24: ✅直接可见 | B24: 网络游戏运营统计>当日"当日付费账号"加总 | C24: 可按日期搜+导出 | D24: P0
A25: ✅直接可见 | B25: 系统统计-报表>"日活"列 | C25: 按日，55453/78340/77011 等 | D25: P0
A26: 🔧待技术 | B26: 系统统计-报表 | C26: 需技术补"7日去重活跃UV"（不是日活累加） | D26: P0
A27: 🔧待技术 | B27: 系统统计-报表 | C27: 需技术补"30日去重活跃UV" | D27: P0
A28: ✅直接可见 | B28: 系统统计-报表>"注册付费人数"列 | C28: 按日，110/351/303 等 | D28: P0
A29: 🔧待技术 | B29: 用户列表+订单管理 | C29: 用户已有"累计充值"字段(评论列表里也可见)；需技术按累计金额分档打标签 | D29: P0
A30: 🔧待技术 | B30: 同上 | C30: 同上 | D30: P0
A31: 🔧待技术 | B31: 同上 | C31: 同上 | D31: P0
... A52: ✅直接可见 | B52: 系统统计>网络游戏运营统计>"新增付费率/活跃付费率/活跃ARPU"列 | C52: 按游戏拆，可导出 | D52: P1
A53: ✅直接可见 | B53: 系统统计>系统统计>"游戏总下载数量"卡片 | C53: 4 | D53: 252 | E53: 320 | F53: P0
A54: ✅直接可见 | B54: 系统统计>套餐统计（套餐类型筛"会员套餐"） | C54: 月月新人卡/月月畅享卡 等档位 | D54: P1
A55: ⚙️派生可算 | B55: 系统统计>套餐统计 + 订单管理 | C55: 需筛同一用户连续多月会员订单 | D55: P1
A56: ✅直接可见 | B56: 系统统计>渠道统计 | C56: 渠道码：1021/1019/1011/recommend/bkxg18 等；同游戏统计字段 | D56: P1
A57: ⚙️派生可算 | B57: 系统统计-报表>"注册付费金额"vs"留存付费金额" | C57: 已经拆好了 ✓ ✓ ✓ | D57: P1
A58: ⚙️派生可算 | B58: 用户管理>订单管理>"支付通道ID"字段 | C58: 大白鯊-微信/大白鯊-支付宝等；可按通道分组 | D58: P1
A59: ⚙️派生可算 | B59: 同上 + 订单状态 | C59: 有效订单/总订单（按通道分组） | D59: P1

Sheet 日明细30天
A1: 系统统计-报表（每日明细 2026-04-28 ~ 2026-05-27）
A2: 来源：系统统计 > 系统统计-报表
A4: 日期 | B4: 日活 | C4: 注册 | D4: 下载数量 | E4: 充值金额 | F4: 投诉扣款订单金额 | G4: 消费G点 | H4: 注册付费人数 | I4: 注册付费金额 | J4: 留存付费人数 | K4: 留存付费金额 | L4: 总下单数 | M4: 有效订单数 | O4: 注册付费率% | P4: 退款率% | Q4: 客单价 | R4: 总付费金额 | S4: 总付费UV(估算)
A5: 2026-05-27 | B5: 78340 | C5: 23912 | D5: 19211 | E5: 68282 | F5: 0 | G5: 610843 | H5: 351 | I5: 19164 | J5: 546 | K5: 49118 | L5: 2024 | M5: 1119 | O5: =H5/C5 | P5: =F5/E5 | Q5: =E5/L5 | R5: =I5+K5 | S5: =H5+J5
A6: 2026-05-26 | B6: 77011 | C6: 23650 | D6: 18701 | E6: 71074 | F6: 0 | G6: 682516 | H6: 303 | I6: 14246 | J6: 552 | K6: 56828 | L6: 2012 | M6: 1096 | O6: =H6/C6 | P6: =F6/E6 | Q6: =E6/L6 | R6: =I6+K6 | S6: =H6+J6
A7: 2026-05-25 | B7: 75886 | C7: 23119 | D7: 17836 | E7: 77934 | F7: 0 | G7: 711140 | H7: 319 | I7: 15942 | J7: 566 | K7: 61992 | L7: 2164 | M7: 1140 | O7: =H7/C7 | P7: =F7/E7 | Q7: =E7/L7 | R7: =I7+K7 | S7: =H7+J7
A8: 2026-05-24 | B8: 114409 | C8: 43143 | D8: 31296 | E8: 83918 | F8: 0 | G8: 761057 | H8: 485 | I8: 28908 | J8: 668 | K8: 55010 | L8: 2906 | M8: 1474 | O8: =H8/C8 | P8: =F8/E8 | Q8: =E8/L8 | R8: =I8+K8 | S8: =H8+J8
A9: 2026-05-23 | B9: 127712 | C9: 53792 | D9: 37144 | E9: 80326 | F9: 0 | G9: 751912 | H9: 468 | I9: 21978 | J9: 641 | K9: 58348 | L9: 3017 | M9: 1397 | O9: =H9/C9 | P9: =F9/E9 | Q9: =E9/L9 | R9: =I9+K9 | S9: =H9+J9
A10: 2026-05-22 | B10: 94801 | C10: 35137 | D10: 26878 | E10: 66186 | F10: 0 | G10: 638275 | H10: 375 | I10: 16080 | J10: 571 | K10: 50106 | L10: 2199 | M10: 1152 | O10: =H10/C10 | P10: =F10/E10 | Q10: =E10/L10 | R10: =I10+K10 | S10: =H10+J10
A11: 2026-05-21 | B11: 77098 | C11: 25954 | D11: 20979 | E11: 69750 | F11: 0 | G11: 610351 | H11: 354 | I11: 22832 | J11: 513 | K11: 46918 | L11: 2301 | M11: 1166 | O11: =H11/C11 | P11: =F11/E11 | Q11: =E11/L11 | R11: =I11+K11 | S11: =H11+J11
A12: 2026-05-20 | B12: 76581 | C12: 27070 | D12: 24128 | E12: 57930 | F12: 0 | G12: 531049 | H12: 317 | I12: 14686 | J12: 486 | K12: 43244 | L12: 1953 | M12: 1003 | O12: =H12/C12 | P12: =F12/E12 | Q12: =E12/L12 | R12: =I12+K12 | S12: =H12+J12
A13: 2026-05-19 | B13: 75069 | C13: 26214 | D13: 23815 | E13: 68068 | F13: 0 | G13: 617204 | H13: 343 | I13: 19556 | J13: 521 | K13: 48512 | L13: 2202 | M13: 1126 | O13: =H13/C13 | P13: =F13/E13 | Q13: =E13/L13 | R13: =I13+K13 | S13: =H13+J13
A14: 2026-05-18 | B14: 74481 | C14: 25628 | D14: 21645 | E14: 80658 | F14: 0 | G14: 749580 | H14: 392 | I14: 20816 | J14: 536 | K14: 59842 | L14: 2330 | M14: 1215 | O14: =H14/C14 | P14: =F14/E14 | Q14: =E14/L14 | R14: =I14+K14 | S14: =H14+J14
A15: 2026-05-17 | B15: 113225 | C15: 48758 | D15: 37927 | E15: 87156 | F15: 0 | G15: 761249 | H15: 471 | I15: 25632 | J15: 625 | K15: 61524 | L15: 2886 | M15: 1361 | O15: =H15/C15 | P15: =F15/E15 | Q15: =E15/L15 | R15: =I15+K15 | S15: =H15+J15
A16: 2026-05-16 | B16: 118928 | C16: 59317 | D16: 51977 | E16: 74484 | F16: 0 | G16: 714148 | H16: 496 | I16: 22338 | J16: 553 | K16: 52146 | L16: 2718 | M16: 1304 | O16: =H16/C16 | P16: =F16/E16 | Q16: =E16/L16 | R16: =I16+K16 | S16: =H16+J16
... A34: 2026-04-28 | B34: 40644 | C34: 22406 | D34: 15596 | E34: 44526 | F34: 0 | G34: 405042 | H34: 175 | I34: 7684 | J34: 347 | K34: 36842 | L34: 1256 | M34: 706 | O34: =H34/C34 | P34: =F34/E34 | Q34: =E34/L34 | R34: =I34+K34 | S34: =H34+J34

Sheet 套餐7天
A1: 套餐统计（近 7 天聚合 2026-05-21 ~ 2026-05-27）
A2: 来源：系统统计 > 套餐统计
A4: 套餐类型 | B4: 套餐名称 | C4: 点击次数 | D4: 点击人数 | E4: 下单次数 | F4: 下单人数 | G4: 成功次数 | H4: 购买金额 | I4: 实际收入 | J4: 点击→下单% | K4: 下单→支付% | L4: 收入占比%
A5: 金币套餐 | B5: Gcoin-648（28） | C5: 276 | D5: 163 | E5: 462 | F5: 265 | G5: 168 | H5: 108864 | I5: 99066.24 | J5: =IFERROR(F5/D5,0) | K5: =IFERROR(G5/F5,0) | L5: =IFERROR(I5/SUM(I5:I16),0)
A6: 金币套餐 | B6: Gcoin-128（26） | C6: 502 | D6: 194 | E6: 1290 | F6: 680 | G6: 625 | H6: 80000 | I6: 72800 | J6: =IFERROR(F6/D6,0) | K6: =IFERROR(G6/F6,0) | L6: =IFERROR(I6/SUM(I5:I16),0)
A7: 金币套餐 | B7: Gcoin-30-新人（23） | C7: 2521 | D7: 1611 | E7: 5515 | F7: 4164 | G7: 2570 | H7: 77100 | I7: 70161 | J7: =IFERROR(F7/D7,0) | K7: =IFERROR(G7/F7,0) | L7: =IFERROR(I7/SUM(I5:I16),0)
A8: 金币套餐 | B8: Gcoin-30（24） | C8: 2144 | D8: 1426 | E8: 4536 | F8: 3200 | G8: 2473 | H8: 74190 | I8: 67512.9 | J8: =IFERROR(F8/D8,0) | K8: =IFERROR(G8/F8,0) | L8: =IFERROR(I8/SUM(I5:I16),0)
A9: 金币套餐 | B9: Gcoin-60（25） | C9: 1434 | D9: 611 | E9: 1408 | F9: 962 | G9: 881 | H9: 52860 | I9: 48102.6 | J9: =IFERROR(F9/D9,0) | K9: =IFERROR(G9/F9,0) | L9: =IFERROR(I9/SUM(I5:I16),0)
A10: 金币套餐 | B10: Gcoin-328（27） | C10: 191 | D10: 111 | E10: 290 | F10: 176 | G10: 155 | H10: 50840 | I10: 46264.4 | J10: =IFERROR(F10/D10,0) | K10: =IFERROR(G10/F10,0) | L10: =IFERROR(I10/SUM(I5:I16),0)
A11: 会员套餐 | B11: 月月畅享卡（9） | C11: 992 | D11: 458 | E11: 1133 | F11: 833 | G11: 709 | H11: 21270 | I11: 19355.7 | J11: =IFERROR(F11/D11,0) | K11: =IFERROR(G11/F11,0) | L11: =IFERROR(I11/SUM(I5:I16),0)
A12: 会员套餐 | B12: 月月新人卡（21） | C12: 1013 | D12: 396 | E12: 1237 | F12: 905 | G12: 702 | H12: 21060 | I12: 19164.6 | J12: =IFERROR(F12/D12,0) | K12: =IFERROR(G12/F12,0) | L12: =IFERROR(I12/SUM(I5:I16),0)
A13: 会员套餐 | B13: 季季畅享卡（10） | C13: 492 | D13: 200 | E13: 481 | F13: 257 | G13: 225 | H13: 19800 | I13: 18018 | J13: =IFERROR(F13/D13,0) | K13: =IFERROR(G13/F13,0) | L13: =IFERROR(I13/SUM(I5:I16),0)
A14: 会员套餐 | B14: 尊享会员永久卡（11） | C14: 553 | D14: 302 | E14: 79 | F14: 66 | G14: 13 | H14: 6344 | I14: 5773.04 | J14: =IFERROR(F14/D14,0) | K14: =IFERROR(G14/F14,0) | L14: =IFERROR(I14/SUM(I5:I16),0)
A15: 会员套餐 | B15: 尊享会员永久卡-新人（12） | C15: 528 | D15: 305 | E15: 66 | F15: 51 | G15: 14 | H15: 4872 | I15: 4433.52 | J15: =IFERROR(F15/D15,0) | K15: =IFERROR(G15/F15,0) | L15: =IFERROR(I15/SUM(I5:I16),0)
A16: 金币套餐 | B16: 老友回归礼包（29） | C16: 14 | D16: 8 | E16: 126 | F16: 110 | G16: 9 | H16: 270 | I16: 245.7 | J16: =IFERROR(F16/D16,0) | K16: =IFERROR(G16/F16,0) | L16: =IFERROR(I16/SUM(I5:I16),0)
A17: 合计 | C17: =SUM(C5:C16) | D17: =SUM(D5:D16) | E17: =SUM(E5:E16) | F17: =SUM(F5:F16) | G17: =SUM(G5:G16) | H17: =SUM(H5:H16) | I17: =SUM(I5:I16)

Sheet 网游TOP
A1: 网游 全 23 款（按充值金额排序，近 7 天 2026-05-21 ~ 2026-05-27）
A2: 来源：系统统计 > 游戏统计；网游名单来自「网络游戏运营统计」共 48 款（其中 25 款 7 天 0 活跃，未列）
A4: 网游名 | B4: 注册 | C4: 日活 | D4: 下载 | E4: 充值金额 | F4: 消费G点 | G4: 注册付费人数 | H4: 注册付费金额 | I4: 留存付费人数 | J4: 留存付费金额 | K4: 充值人数 | L4: 付费率% | M4: ARPU | N4: ARPPU
A5: 性界大战（285） | B5: 46608 | C5: 96550 | D5: 16332 | E5: 207192 | F5: 2100760 | G5: 807 | H5: 46276 | I5: 1276 | J5: 160916 | K5: 2083 | L5: =IFERROR(K5/C5,0) | M5: =IFERROR(E5/C5,0) | N5: =IFERROR(E5/K5,0)
A6: 欲洛降临（456） | B6: 29919 | C6: 52787 | D6: 14878 | E6: 72096 | F6: 641570 | G6: 320 | H6: 18474 | I6: 603 | J6: 53622 | K6: 923 | L6: =IFERROR(K6/C6,0) | M6: =IFERROR(E6/C6,0) | N6: =IFERROR(E6/K6,0)
A7: 决战僵尸舞娘（501） | B7: 44066 | C7: 61181 | D7: 14348 | E7: 52654 | F7: 446600 | G7: 370 | H7: 21018 | I7: 473 | J7: 31636 | K7: 843 | L7: =IFERROR(K7/C7,0) | M7: =IFERROR(E7/C7,0) | N7: =IFERROR(E7/K7,0)
A8: 淫欲斗罗（200） | B8: 2372 | C8: 7378 | D8: 4574 | E8: 13302 | F8: 143590 | G8: 8 | H8: 240 | I8: 115 | J8: 13062 | K8: 123 | L8: =IFERROR(K8/C8,0) | M8: =IFERROR(E8/C8,0) | N8: =IFERROR(E8/K8,0)
A9: 青楼大掌柜（147） | B9: 3910 | C9: 11926 | D9: 18006 | E9: 12384 | F9: 133386 | G9: 35 | H9: 1380 | I9: 88 | J9: 11004 | K9: 123 | L9: =IFERROR(K9/C9,0) | M9: =IFERROR(E9/C9,0) | N9: =IFERROR(E9/K9,0)
A10: 火影娇妻村（151） | B10: 4063 | C10: 6505 | D10: 7632 | E10: 11206 | F10: 116630 | G10: 34 | H10: 2604 | I10: 66 | J10: 8602 | K10: 100 | L10: =IFERROR(K10/C10,0) | M10: =IFERROR(E10/C10,0) | N10: =IFERROR(E10/K10,0)
A11: 异世界后宫物语（489） | B11: 1015 | C11: 3147 | D11: 2275 | E11: 10270 | F11: 110680 | G11: 10 | H11: 1126 | I11: 36 | J11: 9144 | K11: 46 | L11: =IFERROR(K11/C11,0) | M11: =IFERROR(E11/C11,0) | N11: =IFERROR(E11/K11,0)
A12: 淫娘X计划 BT版（383） | B12: 4503 | C12: 4897 | D12: 9213 | E12: 8552 | F12: 78756 | G12: 67 | H12: 3202 | I12: 90 | J12: 5350 | K12: 157 | L12: =IFERROR(K12/C12,0) | M12: =IFERROR(E12/C12,0) | N12: =IFERROR(E12/K12,0)
A13: 欲女神话（150） | B13: 780 | C13: 1598 | D13: 2650 | E13: 6804 | F13: 58660 | G13: 8 | H13: 456 | I13: 40 | J13: 6348 | K13: 48 | L13: =IFERROR(K13/C13,0) | M13: =IFERROR(E13/C13,0) | N13: =IFERROR(E13/K13,0)
A14: 全明星动漫乐园（175） | B14: 1942 | C14: 4050 | D14: 3953 | E14: 5346 | F14: 56450 | G14: 16 | H14: 2456 | I14: 30 | J14: 2890 | K14: 46 | L14: =IFERROR(K14/C14,0) | M14: =IFERROR(E14/C14,0) | N14: =IFERROR(E14/K14,0)
A15: 魅惑前线（273） | B15: 1853 | C15: 4619 | D15: 4064 | E15: 3962 | F15: 46130 | G15: 9 | H15: 398 | I15: 44 | J15: 3564 | K15: 53 | L15: =IFERROR(K15/C15,0) | M15: =IFERROR(E15/C15,0) | N15: =IFERROR(E15/K15,0)
A16: 18禁宝可梦（170） | B16: 1417 | C16: 4849 | D16: 2726 | E16: 3400 | F16: 33550 | G16: 15 | H16: 930 | I16: 45 | J16: 2470 | K16: 60 | L16: =IFERROR(K16/C16,0) | M16: =IFERROR(E16/C16,0) | N16: =IFERROR(E16/K16,0)
... A27: HappyAI（515） | B27: 0 | C27: 0 | D27: 0 | E27: 0 | F27: 0 | G27: 0 | H27: 0 | I27: 0 | J27: 0 | K27: 0 | L27: =IFERROR(K27/C27,0) | M27: =IFERROR(E27/C27,0) | N27: =IFERROR(E27/K27,0)

Sheet 单机TOP
A1: 单机 TOP 20（按消费 G 点排序，近 7 天 2026-05-21 ~ 2026-05-27）
A2: 来源：系统统计 > 游戏统计（剔除"网络游戏运营统计"中的游戏后剩下的即单机）
A3: ⚠️ 单机"充值金额"列全 0，销售额衡量以"消费 G 点"为准（用户下单机付的是 G 点）
A5: 单机名 | B5: 下载量 | C5: 消费G点 | D5: 首次付费人数 | E5: 件均G点
A6: 惩罚少女R（452） | B6: 163 | C6: 39060 | D6: 0 | E6: =IFERROR(C6/B6,0)
A7: 我的幸福人生（357） | B7: 185 | C7: 36354 | D7: 0 | E7: =IFERROR(C7/B7,0)
A8: 同居生活（536） | B8: 170 | C8: 26069 | D8: 0 | E8: =IFERROR(C8/B8,0)
A9: （女拳主義F-ist!）说着国语拳手征服全是顶级女拳的世界（309） | B9: 74 | C9: 18668 | D9: 0 | E9: =IFERROR(C9/B9,0)
A10: 爱撒娇的妹妹两人独处的甜蜜性爱生活（388） | B10: 102 | C10: 17082 | D10: 0 | E10: =IFERROR(C10/B10,0)
A11: 用洗脑APP调教清纯大小姐的模拟游戏（377） | B11: 86 | C11: 15111 | D11: 0 | E11: =IFERROR(C11/B11,0)
A12: 奥特曼的禁断肉棒征服（440） | B12: 69 | C12: 14993 | D12: 0 | E12: =IFERROR(C12/B12,0)
A13: 甜蜜女友3（275） | B13: 46 | C13: 13299 | D13: 0 | E13: =IFERROR(C13/B13,0)
A14: 淫乱性奴调教计划（199） | B14: 63 | C14: 13181 | D14: 0 | E14: =IFERROR(C14/B14,0)
A15: 逆转系统ver.100（328） | B15: 69 | C15: 12051 | D15: 0 | E15: =IFERROR(C15/B15,0)
A16: H版宝可梦：一次性交易大师（310） | B16: 55 | C16: 11960 | D16: 0 | E16: =IFERROR(C16/B16,0)
A17: 星穹轨道-旅行Star Railed（325） | B17: 57 | C17: 11560 | D17: 0 | E17: =IFERROR(C17/B17,0)
... A25: 请让我高潮：魅魔葵夜（503） | B25: 52 | C25: 8541 | D25: 0 | E25: =IFERROR(C25/B25,0)

Sheet 渠道TOP
A1: 渠道 TOP 19（按充值金额排序，近 7 天 2026-05-21 ~ 2026-05-27）
A2: 来源：系统统计 > 渠道统计
A4: 渠道码 | B4: 注册 | C4: 日活 | D4: 下载 | E4: 充值金额 | F4: 消费G点 | G4: 注册付费人数 | H4: 注册付费金额 | I4: 留存付费人数 | J4: 留存付费金额 | K4: 充值人数 | L4: 付费率% | M4: ARPU | N4: ARPPU
A5: official | B5: 110028 | C5: 345234 | D5: 24802 | E5: 269698 | F5: 2716348 | G5: 438 | H5: 17998 | I5: 133 | J5: 201174 | K5: 3197 | L5: =IFERROR(K5/C5,0) | M5: =IFERROR(E5/C5,0) | N5: =IFERROR(E5/K5,0)
A6: 1039 | B6: 10224 | C6: 30070 | D6: 3895 | E6: 35406 | F6: 349656 | G6: 79 | H6: 2736 | I6: 16 | J6: 27078 | K6: 437 | L6: =IFERROR(K6/C6,0) | M6: =IFERROR(E6/C6,0) | N6: =IFERROR(E6/K6,0)
A7: 1036 | B7: 13091 | C7: 29221 | D7: 4899 | E7: 33672 | F7: 306333 | G7: 86 | H7: 2788 | I7: 16 | J7: 25368 | K7: 355 | L7: =IFERROR(K7/C7,0) | M7: =IFERROR(E7/C7,0) | N7: =IFERROR(E7/K7,0)
A8: 1037 | B8: 25888 | C8: 60519 | D8: 8311 | E8: 32922 | F8: 281661 | G8: 107 | H8: 4164 | I8: 22 | J8: 21600 | K8: 531 | L8: =IFERROR(K8/C8,0) | M8: =IFERROR(E8/C8,0) | N8: =IFERROR(E8/K8,0)
A9: 1034 | B9: 16937 | C9: 47882 | D9: 5784 | E9: 26026 | F9: 257760 | G9: 79 | H9: 2638 | I9: 19 | J9: 18866 | K9: 371 | L9: =IFERROR(K9/C9,0) | M9: =IFERROR(E9/C9,0) | N9: =IFERROR(E9/K9,0)
A10: 1033 | B10: 6081 | C10: 17570 | D10: 2255 | E10: 22252 | F10: 203668 | G10: 53 | H10: 2094 | I10: 11 | J10: 17098 | K10: 244 | L10: =IFERROR(K10/C10,0) | M10: =IFERROR(E10/C10,0) | N10: =IFERROR(E10/K10,0)
A11: 1027 | B11: 9249 | C11: 16607 | D11: 8411 | E11: 19884 | F11: 168464 | G11: 88 | H11: 3090 | I11: 13 | J11: 13662 | K11: 323 | L11: =IFERROR(K11/C11,0) | M11: =IFERROR(E11/C11,0) | N11: =IFERROR(E11/K11,0)
A12: 1057 | B12: 7285 | C12: 15471 | D12: 3962 | E12: 11580 | F12: 102539 | G12: 57 | H12: 3128 | I12: 10 | J12: 5372 | K12: 169 | L12: =IFERROR(K12/C12,0) | M12: =IFERROR(E12/C12,0) | N12: =IFERROR(E12/K12,0)
A13: 1038 | B13: 6159 | C13: 13849 | D13: 1319 | E13: 8864 | F13: 71248 | G13: 44 | H13: 1698 | I13: 4 | J13: 4804 | K13: 151 | L13: =IFERROR(K13/C13,0) | M13: =IFERROR(E13/C13,0) | N13: =IFERROR(E13/K13,0)
A14: 3007 | B14: 2891 | C14: 7251 | D14: 1280 | E14: 4440 | F14: 38288 | G14: 19 | H14: 846 | I14: 4 | J14: 2596 | K14: 89 | L14: =IFERROR(K14/C14,0) | M14: =IFERROR(E14/C14,0) | N14: =IFERROR(E14/K14,0)
A15: 1020 | B15: 4302 | C15: 7884 | D15: 4077 | E15: 4154 | F15: 34299 | G15: 39 | H15: 1260 | I15: 7 | J15: 2354 | K15: 111 | L15: =IFERROR(K15/C15,0) | M15: =IFERROR(E15/C15,0) | N15: =IFERROR(E15/K15,0)
A16: 1055 | B16: 3014 | C16: 5909 | D16: 1278 | E16: 3976 | F16: 33963 | G16: 20 | H16: 660 | I16: 3 | J16: 2238 | K16: 68 | L16: =IFERROR(K16/C16,0) | M16: =IFERROR(E16/C16,0) | N16: =IFERROR(E16/K16,0)
... A23: 5000 | B23: 7 | C23: 38 | D23: 5 | E23: 2808 | F23: 28040 | G23: 0 | H23: 0 | I23: 0 | J23: 2808 | K23: 4 | L23: =IFERROR(K23/C23,0) | M23: =IFERROR(E23/C23,0) | N23: =IFERROR(E23/K23,0)

Sheet 平台LTV
A1: 平台 LTV 趋势（按注册日期，2026-04-28 ~ 2026-05-27）
A2: 来源：系统统计 > 网络游戏注册LTV表（按账号数加权聚合到平台口径）
A3: ⚠️ 当前 LTV 仅含网游用户，单机用户 LTV 需技术补
A5: 注册日期 | B5: 总账号 | C5: D1平均LTV | D5: D7平均LTV | E5: D14平均LTV | F5: D30平均LTV
A6: 2026-05-27 | B6: 12631 | C6: 0.804 | D6: 0 | E6: 0 | F6: 0
A7: 2026-05-26 | B7: 12499 | C7: 0.646 | D7: 0 | E7: 0 | F7: 0
A8: 2026-05-25 | B8: 12319 | C8: 0.596 | D8: 0 | E8: 0 | F8: 0
A9: 2026-05-24 | B9: 22326 | C9: 0.581 | D9: 0 | E9: 0 | F9: 0
A10: 2026-05-23 | B10: 27833 | C10: 0.367 | D10: 0 | E10: 0 | F10: 0
A11: 2026-05-22 | B11: 17363 | C11: 0.582 | D11: 1.343 | E11: 0 | F11: 0
A12: 2026-05-21 | B12: 13367 | C12: 1 | D12: 2.941 | E12: 0 | F12: 0
A13: 2026-05-20 | B13: 13585 | C13: 0.475 | D13: 2.25 | E13: 0 | F13: 0
A14: 2026-05-19 | B14: 13515 | C14: 0.664 | D14: 3.294 | E14: 0 | F14: 0
A15: 2026-05-18 | B15: 14168 | C15: 0.598 | D15: 2.24 | E15: 0 | F15: 0
A16: 2026-05-17 | B16: 26571 | C16: 0.471 | D16: 1.331 | E16: 0 | F16: 0
A17: 2026-05-16 | B17: 30131 | C17: 0.369 | D17: 1.639 | E17: 0 | F17: 0
... A35: 2026-04-28 | B35: 5638 | C35: 0.656 | D35: 2.564 | E35: 3.159 | F35: 3.984

Sheet 平台留存
A1: 平台留存趋势（按注册日期，2026-04-28 ~ 2026-05-27）
A2: 来源：系统统计 > 网络游戏注册留存（按注册人数加权聚合到平台口径）
A3: ⚠️ 当前留存为按游戏聚合，平台维度需技术补；"日活统计"页有 bug，无法直接取平台留存
A5: 注册日期 | B5: 注册数 | C5: D1次留率(%) | D5: D3留存率(%) | E5: D7留存率(%) | F5: D14留存率(%) | G5: D30留存率(%)
A6: 2026-05-27 | B6: 12631 | C6: 20.25 | D6: 0 | E6: 0 | F6: 0 | G6: 0
A7: 2026-05-26 | B7: 12499 | C7: 0 | D7: 0 | E7: 0 | F7: 0 | G7: 0
A8: 2026-05-25 | B8: 12319 | C8: 25.38 | D8: 8.28 | E8: 0 | F8: 0 | G8: 0
A9: 2026-05-24 | B9: 22326 | C9: 15.26 | D9: 7.07 | E9: 0 | F9: 0 | G9: 0
A10: 2026-05-23 | B10: 27833 | C10: 21.12 | D10: 6.35 | E10: 0 | F10: 0 | G10: 0
A11: 2026-05-22 | B11: 17363 | C11: 23.69 | D11: 6.71 | E11: 0 | F11: 0 | G11: 0
A12: 2026-05-21 | B12: 13367 | C12: 23.21 | D12: 8.9 | E12: 3.9 | F12: 0 | G12: 0
A13: 2026-05-20 | B13: 13585 | C13: 23.34 | D13: 9.79 | E13: 4.32 | F13: 0 | G13: 0
A14: 2026-05-19 | B14: 13515 | C14: 22.69 | D14: 9.57 | E14: 5.02 | F14: 0 | G14: 0
A15: 2026-05-18 | B15: 14168 | C15: 22.94 | D15: 9.29 | E15: 4.38 | F15: 0 | G15: 0
A16: 2026-05-17 | B16: 26571 | C16: 14.01 | D16: 6.21 | E16: 5.14 | F16: 0 | G16: 0
A17: 2026-05-16 | B17: 30131 | C17: 20.83 | D17: 5.03 | E17: 5.37 | F17: 0 | G17: 0
... A35: 2026-04-28 | B35: 5638 | C35: 23.49 | D35: 10.11 | E35: 5.23 | F35: 3.08 | G35: 0.82

Sheet 日活留存预留
A1: ⚠️ 待技术修复 - 日活统计页面 bug
A2: 后台路径：系统统计 > 日活统计
A5: 【现象】
A6: 该页查询任何日期范围（包括完整的 5/10-5/15）均显示"无数据"
A8: 【字段结构（修好之后用这套）】
A9: 日期 | 当日注册总数 | 今日总活跃(留存) | 次日总活跃(留存) | 3日活跃总数(留存) | 5日活跃总数(留存) | 7日活跃总数(留存) | 15日活跃总数(留存) | 30日活跃总数(留存)
A11: 【临时替代方案】
A12: • 平台 DAU：用本看板「日明细30天」sheet 的"日活"列
A13: • 平台留存：用本看板「平台留存」sheet（按游戏聚合到平台）
A14: • 单游戏留存：直接看后台 系统统计 > 网络游戏注册留存（D1-D30 9 档）
A16: 【要技术做的事】
A17: 排查 日活统计 跑数任务为什么生成不了平台维度的统计数据
